andor_sif/__init__.py
andor_sif/__main__.py
andor_sif/_version.py
andor_sif/cli.py
andor_sif/parser.py
andor_sif-0.0.1.post1.dist-info/LICENSE
andor_sif-0.0.1.post1.dist-info/METADATA
andor_sif-0.0.1.post1.dist-info/WHEEL
andor_sif-0.0.1.post1.dist-info/entry_points.txt
andor_sif-0.0.1.post1.dist-info/top_level.txt
andor_sif-0.0.1.post1.dist-info/RECORD
