Metadata-Version: 2.1
Name: andor-sif
Version: 0.0.1.post1
Summary: .
Home-page: https://github.com/bicarlsen/lifespec_fl.git
Author: Brian Carlsen
Author-email: carlsen.bri@gmail.com
License: UNKNOWN
Keywords: andor,sif,.sif,file
Platform: UNKNOWN
Classifier: Programming Language :: Python :: 3
Classifier: License :: OSI Approved :: MIT License
Classifier: Operating System :: OS Independent
License-File: LICENSE
Requires-Dist: numpy
Requires-Dist: pandas
Requires-Dist: sif-reader
